[{"id":1,"name":"Controller1","auto_start":1,"start_delay":10,"stop_delay":10,"interval":60},
{"id":2,"name":"年兽刷新-改圣诞老人触发怪","stop_delay":30,"interval":600},
{"id":7,"name":"测试-自动激活-改圣诞下雪","interval":21500},
{"id":8,"name":"测试-每月11日激活-改圣诞老人剑仙","stop_delay":3500,"interval":60},
{"id":9,"name":"测试-每周二激活-改圣诞老人积羽","stop_delay":3500,"interval":60},
{"id":10,"name":"测试-任务1-改圣诞老人万化","stop_delay":3500,"interval":60},
{"id":11,"name":"测试-任务2-改圣诞老人祖龙","stop_delay":3500,"interval":60},
{"id":12,"name":"七夕任务凝露石","stop_delay":1800,"interval":60},
{"id":13,"name":"夺宝骑兵――宝箱","stop_delay":7200,"interval":3600},
{"id":14,"name":"月度赛马――宝箱","interval":300},
{"id":15,"name":"月度赛马――报名官、旗竿","interval":439200},
{"id":16,"name":"月度赛马――啦啦队、指示箭头","interval":1800},
{"id":17,"name":"大陆版本初始激活控制器","auto_start":1,"interval":60},
{"id":18,"name":"台湾版本初始激活控制器","interval":60},
{"id":19,"name":"不同版本初始激活控制器3","interval":60},
{"id":20,"name":"不同版本初始激活控制器4","interval":60},
{"id":21,"name":"不同版本初始激活控制器5","interval":60},
{"id":22,"name":"不同版本初始激活控制器6","interval":60},
{"id":23,"name":"不同版本初始激活控制器7","interval":60},
{"id":24,"name":"不激活控制器","interval":60},
{"id":25,"name":"世界BOSS-九子鬼母","auto_start":1,"start_delay":36000,"interval":60},
{"id":26,"name":"30副本青衣冢-门1","auto_start":1,"interval":60},
{"id":27,"name":"40副本幽冥居-门1","auto_start":1,"interval":60},
{"id":28,"name":"40副本幽冥居-门2","auto_start":1,"interval":60},
{"id":29,"name":"40副本幽冥居-门3","auto_start":1,"interval":60},
{"id":30,"name":"40副本幽冥居-机关怪","auto_start":1,"interval":60},
{"id":31,"name":"50副本履霜秘境-门1","auto_start":1,"interval":60},
{"id":32,"name":"50副本履霜秘境-门2","auto_start":1,"interval":60},
{"id":33,"name":"50副本履霜秘境-门3","auto_start":1,"interval":60},
{"id":34,"name":"50副本履霜秘境-门4","auto_start":1,"interval":60},
{"id":35,"name":"50副本履霜秘境-门5","auto_start":1,"interval":60},
{"id":36,"name":"50副本履霜秘境-机关怪5","auto_start":1,"interval":60},
{"id":37,"name":"60副本天劫谷-机关怪","auto_start":1,"interval":60},
{"id":38,"name":"60副本天劫谷-门1金","auto_start":1,"interval":60},
{"id":39,"name":"60副本天劫谷-门2木","auto_start":1,"interval":60},
{"id":40,"name":"60副本天劫谷-门3水","auto_start":1,"interval":60},
{"id":41,"name":"60副本天劫谷-门4火","auto_start":1,"interval":60},
{"id":42,"name":"60副本天劫谷-门5土","auto_start":1,"interval":60},
{"id":43,"name":"70副本怨灵之门-门1","auto_start":1,"interval":60},
{"id":44,"name":"70副本怨灵之门-机关怪2","stop_delay":600,"interval":60},
{"id":45,"name":"70副本怨灵之门-机关怪3","interval":60},
{"id":46,"name":"70副本怨灵之门-门2","auto_start":1,"interval":60},
{"id":47,"name":"70副本怨灵之门-门3","auto_start":1,"interval":60},
{"id":48,"name":"70副本怨灵之门-门4","auto_start":1,"interval":60},
{"id":49,"name":"80副本秘宝窟-门1","auto_start":1,"interval":60},
{"id":50,"name":"80副本秘宝窟-门2","auto_start":1,"interval":60},
{"id":51,"name":"80副本秘宝窟-门3","auto_start":1,"interval":60},
{"id":52,"name":"80副本秘宝窟-门4","auto_start":1,"interval":60},
{"id":53,"name":"80副本秘宝窟-门5","auto_start":1,"interval":60},
{"id":54,"name":"80副本秘宝窟-门6","auto_start":1,"interval":60},
{"id":55,"name":"100副本天劫炼狱-门1","auto_start":1,"interval":60},
{"id":56,"name":"100副本天劫炼狱-门2","auto_start":1,"interval":60},
{"id":57,"name":"100副本天劫炼狱-门3","auto_start":1,"interval":60},
{"id":58,"name":"100副本天劫炼狱-门4","auto_start":1,"interval":60},
{"id":59,"name":"100副本天劫炼狱-门5","auto_start":1,"interval":60},
{"id":60,"name":"100副本天劫炼狱-BOSS绝命","interval":60},
{"id":61,"name":"100副本天劫炼狱-BOSS申屠冥","interval":60},
{"id":62,"name":"100副本天劫炼狱-机关怪2","stop_delay":3600,"interval":60},
{"id":63,"name":"100副本魔域桃源-门1","auto_start":1,"interval":60},
{"id":64,"name":"100副本魔域桃源-门2","auto_start":1,"interval":60},
{"id":65,"name":"100副本魔域桃源-门3","auto_start":1,"interval":60},
{"id":66,"name":"100副本魔域桃源-机关怪","auto_start":1,"interval":60},
{"id":67,"name":"100副本魔域桃源-独角雷尊","interval":60},
{"id":68,"name":"1-100级副本普通怪","auto_start":1,"interval":60},
{"id":69,"name":"1-100级副本普通怪控制怪","interval":60},
{"id":70,"name":"世界稀有宠物通用","auto_start":1,"start_delay":18000,"interval":60},
{"id":71,"name":"大地图怪物攻击－侠隐村","stop_delay":1800,"interval":60},
{"id":72,"name":"大地图怪物攻击－断桥村","stop_delay":1800,"interval":60},
{"id":73,"name":"大地图怪物攻击－倚竹村","stop_delay":1800,"interval":60},
{"id":74,"name":"大地图怪物攻击－四方寨","stop_delay":1800,"interval":60},
{"id":75,"name":"大地图怪物攻击－古风口","stop_delay":1800,"interval":60},
{"id":76,"name":"大地图怪物攻击－南柯寨","stop_delay":1800,"interval":60},
{"id":77,"name":"大地图怪物攻击－伐木场","stop_delay":1800,"interval":60},
{"id":78,"name":"大地图怪物攻击－邻水镇","stop_delay":1800,"interval":60},
{"id":79,"name":"大地图怪物攻击－野人村","stop_delay":1800,"interval":60},
{"id":80,"name":"大地图怪物攻击－镜湖居","stop_delay":1800,"interval":60},
{"id":81,"name":"大地图怪物攻击－幽兰村","stop_delay":1800,"interval":60},
{"id":82,"name":"大地图怪物攻击－联军营地","stop_delay":1800,"interval":60},
{"id":83,"name":"大地图怪物攻击－渔村","stop_delay":1800,"interval":60},
{"id":84,"name":"大地图怪物攻击－疾风部落","stop_delay":1800,"interval":60},
{"id":85,"name":"大地图怪物攻击－信风镇","stop_delay":1800,"interval":60},
{"id":86,"name":"大地图怪物攻击－苏木尔营","stop_delay":1800,"interval":60},
{"id":87,"name":"大地图怪物攻击－落日镇","stop_delay":1800,"interval":60},
{"id":88,"name":"大地图怪物攻击－飞来镇","stop_delay":1800,"interval":60},
{"id":89,"name":"大地图怪物攻击－踏箭山庄","stop_delay":1800,"interval":60},
{"id":90,"name":"大地图怪物攻击－万劫城","stop_delay":1800,"interval":60},
{"id":91,"name":"大地图怪物攻击－獠牙镇","stop_delay":1800,"interval":60},
{"id":92,"name":"大地图怪物攻击－云梦村","stop_delay":1800,"interval":60},
{"id":93,"name":"大地图怪物攻击－砥石寨","stop_delay":1800,"interval":60},
{"id":94,"name":"大地图怪物攻击－迷失村","stop_delay":1800,"interval":60},
{"id":95,"name":"大地图怪物攻击－桃源镇","stop_delay":1800,"interval":60},
{"id":96,"name":"大地图怪物攻击－无为村","stop_delay":1800,"interval":60},
{"id":97,"name":"大地图怪物攻击－胡姬村","stop_delay":1800,"interval":60},
{"id":98,"name":"大地图怪物攻击－沐火村","stop_delay":1800,"interval":60},
{"id":99,"name":"大地图怪物攻击－南屏镇","stop_delay":1800,"interval":60},
{"id":100,"name":"大地图怪物攻击－东屏镇","stop_delay":1800,"interval":60},
{"id":101,"name":"大地图怪物攻击－北屏镇","stop_delay":1800,"interval":60},
{"id":102,"name":"大地图怪物攻击－远征营地","stop_delay":1800,"interval":60},
{"id":103,"name":"大地图怪物攻击－雪霏村","stop_delay":1800,"interval":60},
{"id":104,"name":"大地图怪物攻击－碎冰村","stop_delay":1800,"interval":60},
{"id":105,"name":"大地图怪物攻击－雪崩村","stop_delay":1800,"interval":60},
{"id":106,"name":"大地图怪物攻击－鸣沙村","stop_delay":1800,"interval":60},
{"id":107,"name":"大地图怪物攻击－夜郎村","stop_delay":1800,"interval":60},
{"id":108,"name":"怪物攻城中型-寻梦港","stop_delay":3600,"interval":60},
{"id":109,"name":"怪物攻城中型-万流城","stop_delay":3600,"interval":60},
{"id":110,"name":"寻梦港怪物攻城触发怪","interval":60},
{"id":111,"name":"万流城怪物攻城触发怪","interval":60},
{"id":112,"name":"寻梦港怪物攻城BOSS","start_delay":600,"stop_delay":21600,"interval":60},
{"id":113,"name":"万流城怪物攻城BOSS","start_delay":600,"stop_delay":21600,"interval":60},
{"id":114,"name":"祖龙怪物攻城-第1波小怪","interval":3600},
{"id":115,"name":"祖龙怪物攻城-第2波小怪","interval":60},
{"id":116,"name":"祖龙怪物攻城-第3波小怪","interval":60},
{"id":117,"name":"祖龙怪物攻城-第4波小怪","interval":60},
{"id":118,"name":"祖龙怪物攻城-第5波小怪","interval":60},
{"id":119,"name":"祖龙怪物攻城-第1波BOSS","start_delay":1200,"interval":60},
{"id":120,"name":"祖龙怪物攻城-第2波BOSS","start_delay":1200,"interval":60},
{"id":121,"name":"祖龙怪物攻城-第3波BOSS","start_delay":1200,"interval":60},
{"id":122,"name":"祖龙怪物攻城-第4波BOSS1","start_delay":600,"interval":60},
{"id":123,"name":"祖龙怪物攻城-第4波BOSS2","interval":60},
{"id":124,"name":"祖龙怪物攻城-第4波BOSS3","interval":60},
{"id":125,"name":"祖龙怪物攻城-第5波BOSS副","start_delay":600,"interval":60},
{"id":126,"name":"祖龙怪物攻城-第5波BOSS正","interval":60},
{"id":127,"name":"祖龙怪物攻城-自爆1","interval":60},
{"id":128,"name":"祖龙怪物攻城-自爆2","interval":60},
{"id":129,"name":"祖龙怪物攻城-自爆3","interval":60},
{"id":130,"name":"祖龙怪物攻城-关闭小怪","interval":60},
{"id":131,"name":"祖龙怪物攻城-守城卫兵","interval":3600},
{"id":132,"name":"新年灯笼","interval":622800},
{"id":133,"name":"07年兽祖龙城","stop_delay":1800,"interval":547690},
{"id":134,"name":"07年兽万流城","stop_delay":1800,"interval":547690},
{"id":135,"name":"07年兽寻梦港","stop_delay":1800,"interval":547690},
{"id":136,"name":"07年兽剑仙城","stop_delay":1800,"interval":547690},
{"id":137,"name":"07年兽积羽城","stop_delay":1800,"interval":547690},
{"id":138,"name":"07年兽万化城","stop_delay":1800,"interval":547690},
{"id":140,"name":"台湾版本不激活控制器","interval":60},
{"id":141,"name":"月度赛马保护"}]